
[
  {
    "id": "Barbell_Shrug",
    "name": "槓鈴聳肩",
    "muscleGroup": "Traps",
    "level": "初階",
    "equipment": "槓鈴",
    "primaryMuscles": ["斜方肌"],
    "secondaryMuscles": ["前臂"],
    "description": "最基礎且有效的斜方肌上束訓練動作。",
    "steps": ["雙腳與肩同寬站立，正手握住槓鈴", "手臂自然下垂", "僅利用肩膀向上聳起，盡量靠近耳朵", "頂峰收縮後緩慢下放"],
    "images": "Barbell_Shrug"
  },
  {
    "id": "Barbell_Shrug_Behind_The_Back",
    "name": "背後槓鈴聳肩",
    "muscleGroup": "Traps",
    "level": "中階",
    "equipment": "槓鈴",
    "primaryMuscles": ["斜方肌"],
    "secondaryMuscles": ["前臂", "中背部"],
    "description": "李哈尼 (Lee Haney) 喜愛的動作，能更全面刺激斜方肌中上部。",
    "steps": ["將槓鈴置於身後，正手握槓", "保持胸部挺起", "將肩膀向上聳起", "注意不要過度彎曲手肘"],
    "images": "Barbell_Shrug_Behind_The_Back"
  },
  {
    "id": "Cable_Shrugs",
    "name": "繩索聳肩",
    "muscleGroup": "Traps",
    "level": "初階",
    "equipment": "繩索",
    "primaryMuscles": ["斜方肌"],
    "secondaryMuscles": [],
    "description": "使用繩索提供持續張力。",
    "steps": ["雙手握住低滑輪把手", "站直，手臂伸直", "肩膀向上聳起，感受肌肉收縮", "緩慢回放"],
    "images": "Cable_Shrugs"
  },
  {
    "id": "Calf-Machine_Shoulder_Shrug",
    "name": "小腿機聳肩",
    "muscleGroup": "Traps",
    "level": "初階",
    "equipment": "機械",
    "primaryMuscles": ["斜方肌"],
    "secondaryMuscles": [],
    "description": "利用站姿提踵機的墊肩來進行聳肩，減少握力需求。",
    "steps": ["站在提踵機下，肩膀頂住墊子", "雙手自然下垂或握住把手", "向上聳肩頂起重量", "下放回原位"],
    "images": "Calf-Machine_Shoulder_Shrug"
  },
  {
    "id": "Clean_Shrug",
    "name": "爆發力聳肩 (Clean Shrug)",
    "muscleGroup": "Traps",
    "level": "高階",
    "equipment": "槓鈴",
    "primaryMuscles": ["斜方肌"],
    "secondaryMuscles": ["腿後側", "臀部", "下背"],
    "description": "舉重輔助動作，利用髖部爆發力帶動聳肩。",
    "steps": ["採硬舉起始姿勢", "爆發力伸展髖部和膝蓋", "順勢強力聳肩", "手臂保持伸直，不需拉起槓鈴"],
    "images": "Clean_Shrug"
  },
  {
    "id": "Dumbbell_Shrug",
    "name": "啞鈴聳肩",
    "muscleGroup": "Traps",
    "level": "初階",
    "equipment": "啞鈴",
    "primaryMuscles": ["斜方肌"],
    "secondaryMuscles": [],
    "description": "雙手持啞鈴於體側，軌跡更自然。",
    "steps": ["雙手各持啞鈴垂於身體兩側", "保持手臂伸直", "直上直下聳起肩膀", "避免旋轉肩膀"],
    "images": "Dumbbell_Shrug"
  },
  {
    "id": "Kettlebell_Sumo_High_Pull",
    "name": "壺鈴相撲高拉",
    "muscleGroup": "Traps",
    "level": "中階",
    "equipment": "壺鈴",
    "primaryMuscles": ["斜方肌"],
    "secondaryMuscles": ["肩部", "腿後側", "臀部"],
    "description": "結合下肢爆發力與上肢拉引的全身性動作。",
    "steps": ["寬站距，雙手持壺鈴於雙腿間", "利用髖部爆發力站起", "順勢將壺鈴拉至胸口高度，手肘高於手腕", "下放回起始位置"],
    "images": "Kettlebell_Sumo_High_Pull"
  },
  {
    "id": "Leverage_Shrug",
    "name": "機械式聳肩",
    "muscleGroup": "Traps",
    "level": "初階",
    "equipment": "機械",
    "primaryMuscles": ["斜方肌"],
    "secondaryMuscles": [],
    "description": "固定軌跡，適合大重量訓練。",
    "steps": ["調整座椅或握把高度", "握住握把", "僅利用肩膀向上推動重量", "緩慢下放"],
    "images": "Leverage_Shrug"
  },
  {
    "id": "Low_Pulley_Row_To_Neck",
    "name": "低滑輪頸部划船",
    "muscleGroup": "Traps",
    "level": "中階",
    "equipment": "繩索",
    "primaryMuscles": ["斜方肌"],
    "secondaryMuscles": ["後三角肌", "二頭肌"],
    "description": "類似坐姿划船，但拉向頸部以強調上背與斜方肌。",
    "steps": ["坐姿，使用繩索長桿", "將桿拉向頸部/下巴位置", "手肘向外打開並向後拉", "收縮上背部"],
    "images": "Low_Pulley_Row_To_Neck"
  },
  {
    "id": "Scapular_Pull-Up",
    "name": "肩胛引體向上",
    "muscleGroup": "Traps",
    "level": "初階",
    "equipment": "單槓",
    "primaryMuscles": ["斜方肌下束"],
    "secondaryMuscles": ["前鋸肌", "背闊肌"],
    "description": "強化肩胛控制與下斜方肌的關鍵動作。",
    "steps": ["懸掛於單槓，手臂完全伸直", "僅利用肩胛骨下沉的力量將身體微幅上提", "保持手臂伸直", "放鬆肩胛骨回到懸掛狀態"],
    "images": "Scapular_Pull-Up"
  },
  {
    "id": "Smith_Machine_Behind_the_Back_Shrug",
    "name": "史密斯背後聳肩",
    "muscleGroup": "Traps",
    "level": "中階",
    "equipment": "史密斯機",
    "primaryMuscles": ["斜方肌"],
    "secondaryMuscles": [],
    "description": "利用史密斯機的穩定性進行背後聳肩。",
    "steps": ["背對史密斯機", "雙手在身後握槓", "向上聳肩", "可微彎手肘以避開臀部"],
    "images": "Smith_Machine_Behind_the_Back_Shrug"
  },
  {
    "id": "Smith_Machine_Upright_Row",
    "name": "史密斯直立划船",
    "muscleGroup": "Traps",
    "level": "中階",
    "equipment": "史密斯機",
    "primaryMuscles": ["斜方肌", "三角肌"],
    "secondaryMuscles": ["二頭肌"],
    "description": "固定軌跡的直立划船，需注意肩膀舒適度。",
    "steps": ["站立，正手握槓，握距約與肩同寬", "貼著身體將槓拉至胸口高度", "手肘始終高於手腕", "緩慢下放"],
    "images": "Smith_Machine_Upright_Row"
  },
  {
    "id": "Snatch_Shrug",
    "name": "抓舉聳肩",
    "muscleGroup": "Traps",
    "level": "高階",
    "equipment": "槓鈴",
    "primaryMuscles": ["斜方肌"],
    "secondaryMuscles": ["下背", "腿後側"],
    "description": "寬握距的爆發力聳肩。",
    "steps": ["寬握槓鈴（抓舉握距）", "從大腿中段啟動", "爆發伸髖並聳肩", "手臂保持伸直"],
    "images": "Snatch_Shrug"
  },
  {
    "id": "Standing_Dumbbell_Upright_Row",
    "name": "站姿啞鈴直立划船",
    "muscleGroup": "Traps",
    "level": "中階",
    "equipment": "啞鈴",
    "primaryMuscles": ["斜方肌", "三角肌"],
    "secondaryMuscles": ["二頭肌"],
    "description": "使用啞鈴可減少手腕壓力。",
    "steps": ["雙手持啞鈴於大腿前", "將啞鈴向上拉至胸口", "手肘向外引導動作", "下放"],
    "images": "Standing_Dumbbell_Upright_Row"
  },
  {
    "id": "Upright_Cable_Row",
    "name": "繩索直立划船",
    "muscleGroup": "Traps",
    "level": "中階",
    "equipment": "繩索",
    "primaryMuscles": ["斜方肌", "三角肌"],
    "secondaryMuscles": [],
    "description": "繩索提供持續張力。",
    "steps": ["使用低滑輪直桿或曲桿", "將桿向上拉至下巴下方", "停頓一秒感受收縮", "緩慢回放"],
    "images": "Upright_Cable_Row"
  },
  {
    "id": "Upright_Row_-_With_Bands",
    "name": "彈力帶直立划船",
    "muscleGroup": "Traps",
    "level": "初階",
    "equipment": "彈力帶",
    "primaryMuscles": ["斜方肌", "三角肌"],
    "secondaryMuscles": [],
    "description": "居家或熱身用的直立划船。",
    "steps": ["雙腳踩住彈力帶中段", "雙手握住兩端", "向上拉至胸口高度", "控制回放速度"],
    "images": "Upright_Row_-_With_Bands"
  }
]
